CongtoudaoweiChediLijieKmp/README.md
CongtoudaoweiChediLijieKmp/__init__.py
CongtoudaoweiChediLijieKmp/__main__.py
CongtoudaoweiChediLijieKmp/file.epub
CongtoudaoweiChediLijieKmp/index.html
CongtoudaoweiChediLijieKmp/css/__init__.py
CongtoudaoweiChediLijieKmp/css/annotations.css
CongtoudaoweiChediLijieKmp/css/main.css
CongtoudaoweiChediLijieKmp/css/normalize.css
CongtoudaoweiChediLijieKmp/css/popup.css
CongtoudaoweiChediLijieKmp/font/__init__.py
CongtoudaoweiChediLijieKmp/font/fontello.eot
CongtoudaoweiChediLijieKmp/font/fontello.svg
CongtoudaoweiChediLijieKmp/font/fontello.ttf
CongtoudaoweiChediLijieKmp/font/fontello.woff
CongtoudaoweiChediLijieKmp/img/__init__.py
CongtoudaoweiChediLijieKmp/img/annotator-glyph-sprite.png
CongtoudaoweiChediLijieKmp/img/annotator-icon-sprite.png
CongtoudaoweiChediLijieKmp/img/apple-touch-icon.png
CongtoudaoweiChediLijieKmp/img/cancelfullscreen.png
CongtoudaoweiChediLijieKmp/img/close.png
CongtoudaoweiChediLijieKmp/img/fullscreen.png
CongtoudaoweiChediLijieKmp/img/loader.gif
CongtoudaoweiChediLijieKmp/img/menu-icon.png
CongtoudaoweiChediLijieKmp/img/save.png
CongtoudaoweiChediLijieKmp/img/saved.png
CongtoudaoweiChediLijieKmp/img/settings-s.png
CongtoudaoweiChediLijieKmp/img/settings.png
CongtoudaoweiChediLijieKmp/img/star.png
CongtoudaoweiChediLijieKmp/js/__init__.py
CongtoudaoweiChediLijieKmp/js/epub.js
CongtoudaoweiChediLijieKmp/js/epub.min.js
CongtoudaoweiChediLijieKmp/js/epub.min.map
CongtoudaoweiChediLijieKmp/js/hooks.min.js
CongtoudaoweiChediLijieKmp/js/hooks.min.map
CongtoudaoweiChediLijieKmp/js/reader.js
CongtoudaoweiChediLijieKmp/js/reader.js.map
CongtoudaoweiChediLijieKmp/js/reader.min.js
CongtoudaoweiChediLijieKmp/js/reader.min.map
CongtoudaoweiChediLijieKmp/js/hooks/__init__.py
CongtoudaoweiChediLijieKmp/js/hooks/extensions/__init__.py
CongtoudaoweiChediLijieKmp/js/hooks/extensions/highlight.js
CongtoudaoweiChediLijieKmp/js/libs/__init__.py
CongtoudaoweiChediLijieKmp/js/libs/jquery.min.js
congtoudaowei_chedi_lijie_kmp-2024.3.3.0.dist-info/METADATA
congtoudaowei_chedi_lijie_kmp-2024.3.3.0.dist-info/WHEEL
congtoudaowei_chedi_lijie_kmp-2024.3.3.0.dist-info/entry_points.txt
congtoudaowei_chedi_lijie_kmp-2024.3.3.0.dist-info/top_level.txt
congtoudaowei_chedi_lijie_kmp-2024.3.3.0.dist-info/RECORD
